README.md
setup.py
npose.egg-info/PKG-INFO
npose.egg-info/SOURCES.txt
npose.egg-info/dependency_links.txt
npose.egg-info/requires.txt
npose.egg-info/top_level.txt
npose_util/__init__.py
npose_util/npose_util.py
npose_util_pyrosetta/__init__.py
npose_util_pyrosetta/npose_util_pyrosetta.py
voxel_array/__init__.py
voxel_array/voxel_array.py